{
  "users": {
    "MV_ADMIN": {
      "userId": "MV_ADMIN",
      "userType": "admin",
      "contactMethod": "email",
      "contactValue": "admin@medivault.dev",
      "name": "System Administrator",
      "pinHash": "bcaca3b51737cba46ce1ab0a39897170bacf8ad518ff4970daf39821d011f191",
      "pinSalt": "mvdevsalt",
      "pinLength": 6,
      "passwordHash": null,
      "passwordSalt": null,
      "createdAt": "2026-04-20T21:26:06.952Z"
    }
  },
  "usersByContact": {
    "admin@medivault.dev": "MV_ADMIN"
  },
  "seq": 0
}